odoo/addons/web_healthcheck/__init__.py
odoo/addons/web_healthcheck/__manifest__.py
odoo/addons/web_healthcheck/controllers/__init__.py
odoo/addons/web_healthcheck/controllers/main.py
odoo14_addon_web_healthcheck-14.0.0.0.2.dist-info/METADATA
odoo14_addon_web_healthcheck-14.0.0.0.2.dist-info/WHEEL
odoo14_addon_web_healthcheck-14.0.0.0.2.dist-info/top_level.txt
odoo14_addon_web_healthcheck-14.0.0.0.2.dist-info/RECORD
