Metadata-Version: 2.1
Name: odoo14-addon-web-healthcheck
Version: 14.0.0.0.2
Summary: Odoo Web Health Check
Author: JorgeJuarezM
License: UNKNOWN
Platform: UNKNOWN
Classifier: Programming Language :: Python
Classifier: Framework :: Odoo
Classifier: Framework :: Odoo :: 14.0
Requires-Python: >=3.6
Requires-Dist: odoo (<14.1dev,>=14.0a)
